duplicates.py
find_new.py
picorg.py
rename.py
settings.py
timestamp_finder.py
picorg-0.2.9.dist-info/LICENSE.txt
picorg-0.2.9.dist-info/METADATA
picorg-0.2.9.dist-info/WHEEL
picorg-0.2.9.dist-info/entry_points.txt
picorg-0.2.9.dist-info/top_level.txt
picorg-0.2.9.dist-info/RECORD
