Metadata-Version: 2.1
Name: picorg
Version: 0.2.9
Summary: A script that helps you organize your pictures.
Home-page: https://github.com/frangiz/picorg
Author: Björn Olsson Jarl
Author-email: frangiz@gmail.com
Classifier: Programming Language :: Python :: 3
Classifier: Programming Language :: Python :: 3.8
Classifier: Programming Language :: Python :: 3.9
Classifier: Programming Language :: Python :: 3.10
Classifier: Programming Language :: Python :: 3.11
Classifier: License :: OSI Approved :: MIT License
Classifier: Operating System :: OS Independent
Requires-Python: >=3.8
License-File: LICENSE.txt
Requires-Dist: pillow
Requires-Dist: exifread
Requires-Dist: pydantic
